Metadata-Version: 1.0
Name: baidutest
Version: 0.0.1
Summary: test pip module-wxp
Home-page: https://wxp.com
Author: MySoul
Author-email: 1813057526@qq.com
License: MIT
Keywords: pip,baidutest
Platform: any
